Workbook

Sheet Assumptions
A1: Assumptions
A3: Entry age: | B3: 35
A4: Product: | B4: Term Assurance
A5: Policy term: | B5: 25 | C5: years
A6: Sum Assured: | B6: 100000 | C6: (payable at the end of year of death)
A7: Interest rate: | B7: 0.06
A8: Expense loading: | B8: 1000 | C8: per annum payable at the start of each year
A9: Claim expenses: | B9: 0.005 | C9: of sum assured
A10: Commission: | B10: 0.02 | C10: of all premiums
A11: Mortality table selection: | B11: The mortality rates (qx) have been taken from ONS ( Office for National Statistics), UK Statistics Authority.
A14: Note:
A15: Expense and Commission are assumed to be constant over the years.
A16: Interest rate is assumed to be constant throughout the term.
A17: It is assumed that policy term cannot exceed 50 years.
A18: Premiums are assumed to be paid annually in advance.
A19: Mortality rates assumed to be deterministic (no stochastic mortality modelling).
A20: No lapses or surrenders assumed (policy persists until death or maturity).
A21: No inflation adjustment applied to benefits or expenses.
A22: No profit loading included (equivalence principle pricing).

Sheet Mortality_Table
B1: Notation:
C2: qx | D2: is the mortality rate between age x and (x +1), that is the probability that a person aged x exactly will die before reaching age (x +1).
C3: px | D3: is the probability that a person aged x will live for atleast 1 more year, that is the probability a person aged x will reach age (x+1).
C4: t| qx | D4: is the probability that a person aged x will live for atleast t more years and die tithin the subsequent year, that is the probability a person aged x will reach age (x+t) and die before reaching age (x+t+1).
B6: Age (x) | C6: qx | D6: px
B7: 0 | C7: 0.004602 | D7: =1-C7 -> 0.995398
B8: =B7+1 -> 1 | C8: 0.000247 | D8: =1-C8 -> 0.999753
B9: =B8+1 -> 2 | C9: 0.000177 | D9: =1-C9 -> 0.999823
B10: =B9+1 -> 3 | C10: 0.000115 | D10: =1-C10 -> 0.999885
B11: =B10+1 -> 4 | C11: 0.0001 | D11: =1-C11 -> 0.9999
B12: =B11+1 -> 5 | C12: 9.7e-05 | D12: =1-C12 -> 0.999903
B13: =B12+1 -> 6 | C13: 8e-05 | D13: =1-C13 -> 0.99992
B14: =B13+1 -> 7 | C14: 8e-05 | D14: =1-C14 -> 0.99992
B15: =B14+1 -> 8 | C15: 7.9e-05 | D15: =1-C15 -> 0.999921
B16: =B15+1 -> 9 | C16: 9.1e-05 | D16: =1-C16 -> 0.999909
B17: =B16+1 -> 10 | C17: 7e-05 | D17: =1-C17 -> 0.99993
B18: =B17+1 -> 11 | C18: 9.5e-05 | D18: =1-C18 -> 0.999905
B19: =B18+1 -> 12 | C19: 9.6e-05 | D19: =1-C19 -> 0.999904
... B107: =B106+1 -> 100 | C107: 0.402489 | D107: =1-C107 -> 0.597511

Sheet Pricing_Model
C2: Sum Assured: | D2: =Assumptions!B6 -> 100000 | G2: Interest rate: | H2: =Assumptions!B7 -> 0.06 | S2: Premium: | T2: 1273.1079 | V2: > via goalseek
C3: Claim expenses: | D3: =Assumptions!B6*Assumptions!B9 -> 500 | G3: v: | H3: =1/(1+$H$2) -> 0.94339623 | S3: Equating EPV of Premiums with sum total of EPVs of Benefits and Expesnes
C4: Total: | D4: =SUM(D2:D3) -> 100500 | S4: EPV of expenses + EPV of benefits: | Y4: =X60+M60 -> 16594.666
C6: EPV of Benefits | R6: EPV of Premiums & Expenses
C8: Policy year (t) | D8: Age (x) | E8: qx | F8: px | G8: ="tp"&D9 -> tp35 | H8: ="t-1| q"&D9 -> t-1| q35 | I8: Benefits | J8: Claim expenses | K8: Interest rate | L8: Discount rate | M8: EPV | R8: =C8 -> Policy year (t) | S8: =D8 -> Age (x) | T8: Expenses | U8: Commission | V8: =G8 -> tp35 | W8: Premiums | X8: EPV of Expenses | Y8: EPV of Premiums less commission
C9: 1 | D9: =Assumptions!B3 -> 35 | E9: =VLOOKUP(D9,Mortality_Table!B7:D107,2,0) -> 0.00111 | F9: =IF(E9=0,0,1-E9) -> 0.99889 | G9: =F9 -> 0.99889 | H9: =E9 -> 0.00111 | I9: =Assumptions!B6 -> 100000 | J9: =Assumptions!$B$9*Assumptions!B6 -> 500 | K9: =Assumptions!$B$7 -> 0.06 | L9: =1/(1+K9) -> 0.94339623 | M9: =(I9+J9)*H9*L9^C9 -> 105.24057 | R9: =C9 -> 1 | S9: =D9 -> 35 | T9: =Assumptions!B8 -> 1000 | U9: =Assumptions!$B$10*Pricing_Model!$T$2 -> 25.462159 | V9: =G9 -> 0.99889 | W9: =T2 -> 1273.1079 | X9: =(T9) -> 1000 | Y9: =W9-U9 -> 1247.6458
C10: =C9+1 -> 2 | D10: =D9+1 -> 36 | E10: =VLOOKUP(D10,Mortality_Table!B8:D108,2,0) -> 0.001233 | F10: =IF(E10=0,0,1-E10) -> 0.998767 | G10: =G9*F10 -> 0.99765837 | H10: =G9*E10 -> 0.0012316314 | I10: =IF(C10<=Assumptions!$B$5,Pricing_Model!I9,0) -> 100000 | J10: =IF(C10<=Assumptions!$B$5,Pricing_Model!J9,0) -> 500 | K10: =K9 -> 0.06 | L10: =1/(1+K10) -> 0.94339623 | M10: =(I10+J10)*H10*L10^C10 -> 110.16283 | R10: =C10 -> 2 | S10: =D10 -> 36 | T10: =IF(R10<=Assumptions!$B$5,Pricing_Model!T9,0) -> 1000 | U10: =IF(R10<=Assumptions!$B$5,Pricing_Model!U9,0) -> 25.462159 | V10: =G10 -> 0.99765837 | W10: =IF(R10<=Assumptions!$B$5,Pricing_Model!W9,0) -> 1273.1079 | X10: =(T10)*V9*L10^R9 -> 942.34906 | Y10: =(W10-U10)*V9*L10^R9 -> 1175.7178
C11: =C10+1 -> 3 | D11: =D10+1 -> 37 | E11: =VLOOKUP(D11,Mortality_Table!B9:D109,2,0) -> 0.001305 | F11: =IF(E11=0,0,1-E11) -> 0.998695 | G11: =G10*F11 -> 0.99635642 | H11: =G10*E11 -> 0.0013019442 | I11: =IF(C11<=Assumptions!$B$5,Pricing_Model!I10,0) -> 100000 | J11: =IF(C11<=Assumptions!$B$5,Pricing_Model!J10,0) -> 500 | K11: =K10 -> 0.06 | L11: =1/(1+K11) -> 0.94339623 | M11: =(I11+J11)*H11*L11^C11 -> 109.86031 | R11: =C11 -> 3 | S11: =D11 -> 37 | T11: =IF(R11<=Assumptions!$B$5,Pricing_Model!T10,0) -> 1000 | U11: =IF(R11<=Assumptions!$B$5,Pricing_Model!U10,0) -> 25.462159 | V11: =G11 -> 0.99635642 | W11: =IF(R11<=Assumptions!$B$5,Pricing_Model!W10,0) -> 1273.1079 | X11: =(T11)*V10*L11^R10 -> 887.9124 | Y11: =(W11-U11)*V10*L11^R10 -> 1107.8002
C12: =C11+1 -> 4 | D12: =D11+1 -> 38 | E12: =VLOOKUP(D12,Mortality_Table!B10:D110,2,0) -> 0.00137 | F12: =IF(E12=0,0,1-E12) -> 0.99863 | G12: =G11*F12 -> 0.99499142 | H12: =G11*E12 -> 0.0013650083 | I12: =IF(C12<=Assumptions!$B$5,Pricing_Model!I11,0) -> 100000 | J12: =IF(C12<=Assumptions!$B$5,Pricing_Model!J11,0) -> 500 | K12: =K11 -> 0.06 | L12: =1/(1+K12) -> 0.94339623 | M12: =(I12+J12)*H12*L12^C12 -> 108.66205 | R12: =C12 -> 4 | S12: =D12 -> 38 | T12: =IF(R12<=Assumptions!$B$5,Pricing_Model!T11,0) -> 1000 | U12: =IF(R12<=Assumptions!$B$5,Pricing_Model!U11,0) -> 25.462159 | V12: =G12 -> 0.99499142 | W12: =IF(R12<=Assumptions!$B$5,Pricing_Model!W11,0) -> 1273.1079 | X12: =(T12)*V11*L12^R11 -> 836.56007 | Y12: =(W12-U12)*V11*L12^R11 -> 1043.7306
C13: =C12+1 -> 5 | D13: =D12+1 -> 39 | E13: =VLOOKUP(D13,Mortality_Table!B11:D111,2,0) -> 0.001517 | F13: =IF(E13=0,0,1-E13) -> 0.998483 | G13: =G12*F13 -> 0.99348201 | H13: =G12*E13 -> 0.001509402 | I13: =IF(C13<=Assumptions!$B$5,Pricing_Model!I12,0) -> 100000 | J13: =IF(C13<=Assumptions!$B$5,Pricing_Model!J12,0) -> 500 | K13: =K12 -> 0.06 | L13: =1/(1+K13) -> 0.94339623 | M13: =(I13+J13)*H13*L13^C13 -> 113.35525 | R13: =C13 -> 5 | S13: =D13 -> 39 | T13: =IF(R13<=Assumptions!$B$5,Pricing_Model!T12,0) -> 1000 | U13: =IF(R13<=Assumptions!$B$5,Pricing_Model!U12,0) -> 25.462159 | V13: =G13 -> 0.99348201 | W13: =IF(R13<=Assumptions!$B$5,Pricing_Model!W12,0) -> 1273.1079 | X13: =(T13)*V12*L13^R12 -> 788.1264 | Y13: =(W13-U13)*V12*L13^R12 -> 983.30257
C14: =C13+1 -> 6 | D14: =D13+1 -> 40 | E14: =VLOOKUP(D14,Mortality_Table!B12:D112,2,0) -> 0.001681 | F14: =IF(E14=0,0,1-E14) -> 0.998319 | G14: =G13*F14 -> 0.99181197 | H14: =G13*E14 -> 0.0016700433 | I14: =IF(C14<=Assumptions!$B$5,Pricing_Model!I13,0) -> 100000 | J14: =IF(C14<=Assumptions!$B$5,Pricing_Model!J13,0) -> 500 | K14: =K13 -> 0.06 | L14: =1/(1+K14) -> 0.94339623 | M14: =(I14+J14)*H14*L14^C14 -> 118.32012 | R14: =C14 -> 6 | S14: =D14 -> 40 | T14: =IF(R14<=Assumptions!$B$5,Pricing_Model!T13,0) -> 1000 | U14: =IF(R14<=Assumptions!$B$5,Pricing_Model!U13,0) -> 25.462159 | V14: =G14 -> 0.99181197 | W14: =IF(R14<=Assumptions!$B$5,Pricing_Model!W13,0) -> 1273.1079 | X14: =(T14)*V13*L14^R13 -> 742.38755 | Y14: =(W14-U14)*V13*L14^R13 -> 926.2367
C15: =C14+1 -> 7 | D15: =D14+1 -> 41 | E15: =VLOOKUP(D15,Mortality_Table!B13:D113,2,0) -> 0.001808 | F15: =IF(E15=0,0,1-E15) -> 0.998192 | G15: =G14*F15 -> 0.99001877 | H15: =G14*E15 -> 0.001793196 | I15: =IF(C15<=Assumptions!$B$5,Pricing_Model!I14,0) -> 100000 | J15: =IF(C15<=Assumptions!$B$5,Pricing_Model!J14,0) -> 500 | K15: =K14 -> 0.06 | L15: =1/(1+K15) -> 0.94339623 | M15: =(I15+J15)*H15*L15^C15 -> 119.85407 | R15: =C15 -> 7 | S15: =D15 -> 41 | T15: =IF(R15<=Assumptions!$B$5,Pricing_Model!T14,0) -> 1000 | U15: =IF(R15<=Assumptions!$B$5,Pricing_Model!U14,0) -> 25.462159 | V15: =G15 -> 0.99001877 | W15: =IF(R15<=Assumptions!$B$5,Pricing_Model!W14,0) -> 1273.1079 | X15: =(T15)*V14*L15^R14 -> 699.1883 | Y15: =(W15-U15)*V14*L15^R14 -> 872.33933
C16: =C15+1 -> 8 | D16: =D15+1 -> 42 | E16: =VLOOKUP(D16,Mortality_Table!B14:D114,2,0) -> 0.00189 | F16: =IF(E16=0,0,1-E16) -> 0.99811 | G16: =G15*F16 -> 0.98814764 | H16: =G15*E16 -> 0.0018711355 | I16: =IF(C16<=Assumptions!$B$5,Pricing_Model!I15,0) -> 100000 | J16: =IF(C16<=Assumptions!$B$5,Pricing_Model!J15,0) -> 500 | K16: =K15 -> 0.06 | L16: =1/(1+K16) -> 0.94339623 | M16: =(I16+J16)*H16*L16^C16 -> 117.98434 | R16: =C16 -> 8 | S16: =D16 -> 42 | T16: =IF(R16<=Assumptions!$B$5,Pricing_Model!T15,0) -> 1000 | U16: =IF(R16<=Assumptions!$B$5,Pricing_Model!U15,0) -> 25.462159 | V16: =G16 -> 0.98814764 | W16: =IF(R16<=Assumptions!$B$5,Pricing_Model!W15,0) -> 1273.1079 | X16: =(T16)*V15*L16^R15 -> 658.41903 | Y16: =(W16-U16)*V15*L16^R15 -> 821.47372
C17: =C16+1 -> 9 | D17: =D16+1 -> 43 | E17: =VLOOKUP(D17,Mortality_Table!B15:D115,2,0) -> 0.002074 | F17: =IF(E17=0,0,1-E17) -> 0.997926 | G17: =G16*F17 -> 0.98609822 | H17: =G16*E17 -> 0.0020494182 | I17: =IF(C17<=Assumptions!$B$5,Pricing_Model!I16,0) -> 100000 | J17: =IF(C17<=Assumptions!$B$5,Pricing_Model!J16,0) -> 500 | K17: =K16 -> 0.06 | L17: =1/(1+K17) -> 0.94339623 | M17: =(I17+J17)*H17*L17^C17 -> 121.91127 | R17: =C17 -> 9 | S17: =D17 -> 43 | T17: =IF(R17<=Assumptions!$B$5,Pricing_Model!T16,0) -> 1000 | U17: =IF(R17<=Assumptions!$B$5,Pricing_Model!U16,0) -> 25.462159 | V17: =G17 -> 0.98609822 | W17: =IF(R17<=Assumptions!$B$5,Pricing_Model!W16,0) -> 1273.1079 | X17: =(T17)*V16*L17^R16 -> 619.97605 | Y17: =(W17-U17)*V16*L17^R16 -> 773.51051
C18: =C17+1 -> 10 | D18: =D17+1 -> 44 | E18: =VLOOKUP(D18,Mortality_Table!B16:D116,2,0) -> 0.002164 | F18: =IF(E18=0,0,1-E18) -> 0.997836 | G18: =G17*F18 -> 0.9839643 | H18: =G17*E18 -> 0.0021339166 | I18: =IF(C18<=Assumptions!$B$5,Pricing_Model!I17,0) -> 100000 | J18: =IF(C18<=Assumptions!$B$5,Pricing_Model!J17,0) -> 500 | K18: =K17 -> 0.06 | L18: =1/(1+K18) -> 0.94339623 | M18: =(I18+J18)*H18*L18^C18 -> 119.75257 | R18: =C18 -> 10 | S18: =D18 -> 44 | T18: =IF(R18<=Assumptions!$B$5,Pricing_Model!T17,0) -> 1000 | U18: =IF(R18<=Assumptions!$B$5,Pricing_Model!U17,0) -> 25.462159 | V18: =G18 -> 0.9839643 | W18: =IF(R18<=Assumptions!$B$5,Pricing_Model!W17,0) -> 1273.1079 | X18: =(T18)*V17*L18^R17 -> 583.67002 | Y18: =(W18-U18)*V17*L18^R17 -> 728.21344
C19: =C18+1 -> 11 | D19: =D18+1 -> 45 | E19: =VLOOKUP(D19,Mortality_Table!B17:D117,2,0) -> 0.002433 | F19: =IF(E19=0,0,1-E19) -> 0.997567 | G19: =G18*F19 -> 0.98157032 | H19: =G18*E19 -> 0.0023939852 | I19: =IF(C19<=Assumptions!$B$5,Pricing_Model!I18,0) -> 100000 | J19: =IF(C19<=Assumptions!$B$5,Pricing_Model!J18,0) -> 500 | K19: =K18 -> 0.06 | L19: =1/(1+K19) -> 0.94339623 | M19: =(I19+J19)*H19*L19^C19 -> 126.74271 | R19: =C19 -> 11 | S19: =D19 -> 45 | T19: =IF(R19<=Assumptions!$B$5,Pricing_Model!T18,0) -> 1000 | U19: =IF(R19<=Assumptions!$B$5,Pricing_Model!U18,0) -> 25.462159 | V19: =G19 -> 0.98157032 | W19: =IF(R19<=Assumptions!$B$5,Pricing_Model!W18,0) -> 1273.1079 | X19: =(T19)*V18*L19^R18 -> 549.44053 | Y19: =(W19-U19)*V18*L19^R18 -> 685.50715
C20: =C19+1 -> 12 | D20: =D19+1 -> 46 | E20: =VLOOKUP(D20,Mortality_Table!B18:D118,2,0) -> 0.002615 | F20: =IF(E20=0,0,1-E20) -> 0.997385 | G20: =G19*F20 -> 0.97900351 | H20: =G19*E20 -> 0.0025668064 | I20: =IF(C20<=Assumptions!$B$5,Pricing_Model!I19,0) -> 100000 | J20: =IF(C20<=Assumptions!$B$5,Pricing_Model!J19,0) -> 500 | K20: =K19 -> 0.06 | L20: =1/(1+K20) -> 0.94339623 | M20: =(I20+J20)*H20*L20^C20 -> 128.20023 | R20: =C20 -> 12 | S20: =D20 -> 46 | T20: =IF(R20<=Assumptions!$B$5,Pricing_Model!T19,0) -> 1000 | U20: =IF(R20<=Assumptions!$B$5,Pricing_Model!U19,0) -> 25.462159 | V20: =G20 -> 0.97900351 | W20: =IF(R20<=Assumptions!$B$5,Pricing_Model!W19,0) -> 1273.1079 | X20: =(T20)*V19*L20^R19 -> 517.079 | Y20: =(W20-U20)*V19*L20^R19 -> 645.13143
C21: =C20+1 -> 13 | D21: =D20+1 -> 47 | E21: =VLOOKUP(D21,Mortality_Table!B19:D119,2,0) -> 0.002839 | F21: =IF(E21=0,0,1-E21) -> 0.997161 | G21: =G20*F21 -> 0.97622412 | H21: =G20*E21 -> 0.002779391 | I21: =IF(C21<=Assumptions!$B$5,Pricing_Model!I20,0) -> 100000 | J21: =IF(C21<=Assumptions!$B$5,Pricing_Model!J20,0) -> 500 | K21: =K20 -> 0.06 | L21: =1/(1+K21) -> 0.94339623 | M21: =(I21+J21)*H21*L21^C21 -> 130.96024 | R21: =C21 -> 13 | S21: =D21 -> 47 | T21: =IF(R21<=Assumptions!$B$5,Pricing_Model!T20,0) -> 1000 | U21: =IF(R21<=Assumptions!$B$5,Pricing_Model!U20,0) -> 25.462159 | V21: =G21 -> 0.97622412 | W21: =IF(R21<=Assumptions!$B$5,Pricing_Model!W20,0) -> 1273.1079 | X21: =(T21)*V20*L21^R20 -> 486.53475 | Y21: =(W21-U21)*V20*L21^R20 -> 607.02303
... C58: =C57+1 -> 50 | D58: =D57+1 -> 84 | E58: =VLOOKUP(D58,Mortality_Table!B56:D156,2,0) -> 0.084093 | F58: =IF(E58=0,0,1-E58) -> 0.915907 | G58: =G57*F58 -> 0.41862031 | H58: =G57*E58 -> 0.038435166 | I58: =IF(C58<=Assumptions!$B$5,Pricing_Model!I57,0) -> 0 | J58: =IF(C58<=Assumptions!$B$5,Pricing_Model!J57,0) -> 0 | K58: =K57 -> 0.06 | L58: =1/(1+K58) -> 0.94339623 | M58: =(I58+J58)*H58*L58^C58 -> 0 | R58: =C58 -> 50 | S58: =D58 -> 84 | T58: =IF(R58<=Assumptions!$B$5,Pricing_Model!T57,0) -> 0 | U58: =IF(R58<=Assumptions!$B$5,Pricing_Model!U57,0) -> 0 | V58: =G58 -> 0.41862031 | W58: =IF(R58<=Assumptions!$B$5,Pricing_Model!W57,0) -> 0 | X58: =(T58)*V57*L58^R57 -> 0 | Y58: =(W58-U58)*V57*L58^R57 -> 0
L60: Total: | M60: =SUM(M9:M58) -> 3293.88 | W60: Total: | X60: =SUM(X9:X58) -> 13300.786 | Y60: =SUM(Y9:Y34) -> 16594.67 | Z60: >> | AA60: Set this cell to equate the total EPV of benefits and expenses.

Sheet Reserving_Model
B1: Notation: | C1: TA:x:<n> | D1: It is the expected present value of 1 unit payable at the end of the year of death of a life aged x, provided death occurs within the next n years.
C2: aduex:<n> | D2: It is the expected present value of 1 unit payable at the start of each year for a maximum of n years, provided the life aged x is alive at the time of payment.
C5: Premium: | D5: =Pricing_Model!$T$2 -> 1273.1079 | M5: Sum Assured: | N5: =Assumptions!$B$6 -> 100000 | Q5: Interest rate: | R5: =Assumptions!B7 -> 0.06 | V5: Maximum Absolute Differece: | Y5: =MAX(V11:V60) -> 0.016656322
C6: Commission: | D6: =Assumptions!$B$10*Reserving_Model!$D$5 -> 25.462159 | M6: Claim expenses: | N6: =Assumptions!B9*Assumptions!B6 -> 500 | Q6: v: | R6: =1/(1+$R$5) -> 0.94339623
C7: Expenses: | D7: =Assumptions!B8 -> 1000 | M7: Total: | N7: =SUM(N5:N6) -> 100500
B10: Policy year (t) | C10: Age (x) | D10: qx | E10: px | F10: Premiums | G10: Commission | H10: Expenses | I10: Sum Assured | J10: Claim expenses | K10: Interest rate | L10: Discount rate | M10: TA:x:<n> | N10: aduex:<n> | O10: PV of premiums to start of year | P10: PV of expenses to start of year | Q10: PV of benefits to start of year | R10: Prospective reserve at start of year | S10: Prospective reserve at end of year | T10: Retrospective reserve at end of year | V10: Absolute difference | W10: Tolerance
B11: =Pricing_Model!C9 -> 1 | C11: =Assumptions!B3 -> 35 | D11: =VLOOKUP(C11,Mortality_Table!B7:D107,2,0) -> 0.00111 | E11: =1-D11 -> 0.99889 | F11: =Pricing_Model!W9 -> 1273.1079 | G11: =Pricing_Model!U9 -> 25.462159 | H11: =Pricing_Model!T9 -> 1000 | I11: =Pricing_Model!I9 -> 100000 | J11: =Pricing_Model!J9 -> 500 | K11: =Pricing_Model!K9 -> 0.06 | L11: =Pricing_Model!L9 -> 0.94339623 | M11: =IF(B11<=Assumptions!$B$5,Reserving_Model!L11*Reserving_Model!E11*Reserving_Model!M12+Reserving_Model!L11*Reserving_Model!D11,0) -> 0.032774926 | N11: =IF(B11<=Assumptions!$B$5, 1+N12*L11*E11,0) -> 13.300786 | O11: =N11*(F11-G11) -> 16594.67 | P11: =H11*N11 -> 13300.786 | Q11: =(I11+J11)*M11 -> 3293.88 | R11: =Q11+P11-O11 -> -0.0035702888 | S11: =R12 -> 151.11347 | T11: =IF(B11<=Assumptions!$B$5, ((F11-G11-H11)*(1+K11)-((I11+J11)*D11))/E11, 0) -> 151.11726 | V11: =ABS(T11-S11) -> 0.0037887117 | W11: =IF(B11<=Assumptions!$B$5, IF(V11<0.1,"OK","CHECK"),0) -> OK
B12: =Pricing_Model!C10 -> 2 | C12: =C11+1 -> 36 | D12: =VLOOKUP(C12,Mortality_Table!B8:D108,2,0) -> 0.001233 | E12: =1-D12 -> 0.998767 | F12: =Pricing_Model!W10 -> 1273.1079 | G12: =Pricing_Model!U10 -> 25.462159 | H12: =Pricing_Model!T10 -> 1000 | I12: =Pricing_Model!I10 -> 100000 | J12: =Pricing_Model!J10 -> 500 | K12: =Pricing_Model!K10 -> 0.06 | L12: =Pricing_Model!L10 -> 0.94339623 | M12: =IF(B12<=Assumptions!$B$5,Reserving_Model!L12*Reserving_Model!E12*Reserving_Model!M13+Reserving_Model!L12*Reserving_Model!D12,0) -> 0.033668793 | N12: =IF(B12<=Assumptions!$B$5, 1+N13*L12*E12,0) -> 13.053323 | O12: =N12*(F12-G12) -> 16285.923 | P12: =H12*N12 -> 13053.323 | Q12: =(I12+J12)*M12 -> 3383.7137 | R12: =Q12+P12-O12 -> 151.11347 | S12: =R13 -> 299.13714 | T12: =IF(B12<=Assumptions!$B$5, ((T11+F12-G12-H12)*(1+K12)-((I12+J12)*D12))/E12, 0) -> 299.14116 | V12: =ABS(T12-S12) -> 0.0040209922 | W12: =IF(B12<=Assumptions!$B$5, IF(V12<0.1,"OK","CHECK"),0) -> OK
B13: =Pricing_Model!C11 -> 3 | C13: =C12+1 -> 37 | D13: =VLOOKUP(C13,Mortality_Table!B9:D109,2,0) -> 0.001305 | E13: =1-D13 -> 0.998695 | F13: =Pricing_Model!W11 -> 1273.1079 | G13: =Pricing_Model!U11 -> 25.462159 | H13: =Pricing_Model!T11 -> 1000 | I13: =Pricing_Model!I11 -> 100000 | J13: =Pricing_Model!J11 -> 500 | K13: =Pricing_Model!K11 -> 0.06 | L13: =Pricing_Model!L11 -> 0.94339623 | M13: =IF(B13<=Assumptions!$B$5,Reserving_Model!L13*Reserving_Model!E13*Reserving_Model!M14+Reserving_Model!L13*Reserving_Model!D13,0) -> 0.034498458 | N13: =IF(B13<=Assumptions!$B$5, 1+N14*L13*E13,0) -> 12.792295 | O13: =N13*(F13-G13) -> 15960.253 | P13: =H13*N13 -> 12792.295 | Q13: =(I13+J13)*M13 -> 3467.095 | R13: =Q13+P13-O13 -> 299.13714 | S13: =R14 -> 449.02337 | T13: =IF(B13<=Assumptions!$B$5, ((T12+F13-G13-H13)*(1+K13)-((I13+J13)*D13))/E13, 0) -> 449.02764 | V13: =ABS(T13-S13) -> 0.0042678213 | W13: =IF(B13<=Assumptions!$B$5, IF(V13<0.1,"OK","CHECK"),0) -> OK
B14: =Pricing_Model!C12 -> 4 | C14: =C13+1 -> 38 | D14: =VLOOKUP(C14,Mortality_Table!B10:D110,2,0) -> 0.00137 | E14: =1-D14 -> 0.99863 | F14: =Pricing_Model!W12 -> 1273.1079 | G14: =Pricing_Model!U12 -> 25.462159 | H14: =Pricing_Model!T12 -> 1000 | I14: =Pricing_Model!I12 -> 100000 | J14: =Pricing_Model!J12 -> 500 | K14: =Pricing_Model!K12 -> 0.06 | L14: =Pricing_Model!L12 -> 0.94339623 | M14: =IF(B14<=Assumptions!$B$5,Reserving_Model!L14*Reserving_Model!E14*Reserving_Model!M15+Reserving_Model!L14*Reserving_Model!D14,0) -> 0.035309444 | N14: =IF(B14<=Assumptions!$B$5, 1+N15*L14*E14,0) -> 12.516166 | O14: =N14*(F14-G14) -> 15615.742 | P14: =H14*N14 -> 12516.166 | Q14: =(I14+J14)*M14 -> 3548.5991 | R14: =Q14+P14-O14 -> 449.02337 | S14: =R15 -> 601.6085 | T14: =IF(B14<=Assumptions!$B$5, ((T13+F14-G14-H14)*(1+K14)-((I14+J14)*D14))/E14, 0) -> 601.61303 | V14: =ABS(T14-S14) -> 0.0045300968 | W14: =IF(B14<=Assumptions!$B$5, IF(V14<0.1,"OK","CHECK"),0) -> OK
B15: =Pricing_Model!C13 -> 5 | C15: =C14+1 -> 39 | D15: =VLOOKUP(C15,Mortality_Table!B11:D111,2,0) -> 0.001517 | E15: =1-D15 -> 0.998483 | F15: =Pricing_Model!W13 -> 1273.1079 | G15: =Pricing_Model!U13 -> 25.462159 | H15: =Pricing_Model!T13 -> 1000 | I15: =Pricing_Model!I13 -> 100000 | J15: =Pricing_Model!J13 -> 500 | K15: =Pricing_Model!K13 -> 0.06 | L15: =Pricing_Model!L13 -> 0.94339623 | M15: =IF(B15<=Assumptions!$B$5,Reserving_Model!L15*Reserving_Model!E15*Reserving_Model!M16+Reserving_Model!L15*Reserving_Model!D15,0) -> 0.036107478 | N15: =IF(B15<=Assumptions!$B$5, 1+N16*L15*E15,0) -> 12.223883 | O15: =N15*(F15-G15) -> 15251.076 | P15: =H15*N15 -> 12223.883 | Q15: =(I15+J15)*M15 -> 3628.8015 | R15: =Q15+P15-O15 -> 601.6085 | S15: =R16 -> 748.88709 | T15: =IF(B15<=Assumptions!$B$5, ((T14+F15-G15-H15)*(1+K15)-((I15+J15)*D15))/E15, 0) -> 748.8919 | V15: =ABS(T15-S15) -> 0.0048091981 | W15: =IF(B15<=Assumptions!$B$5, IF(V15<0.1,"OK","CHECK"),0) -> OK
B16: =Pricing_Model!C14 -> 6 | C16: =C15+1 -> 40 | D16: =VLOOKUP(C16,Mortality_Table!B12:D112,2,0) -> 0.001681 | E16: =1-D16 -> 0.998319 | F16: =Pricing_Model!W14 -> 1273.1079 | G16: =Pricing_Model!U14 -> 25.462159 | H16: =Pricing_Model!T14 -> 1000 | I16: =Pricing_Model!I14 -> 100000 | J16: =Pricing_Model!J14 -> 500 | K16: =Pricing_Model!K14 -> 0.06 | L16: =Pricing_Model!L14 -> 0.94339623 | M16: =IF(B16<=Assumptions!$B$5,Reserving_Model!L16*Reserving_Model!E16*Reserving_Model!M17+Reserving_Model!L16*Reserving_Model!D16,0) -> 0.036812771 | N16: =IF(B16<=Assumptions!$B$5, 1+N17*L16*E16,0) -> 11.915392 | O16: =N16*(F16-G16) -> 14866.188 | P16: =H16*N16 -> 11915.392 | Q16: =(I16+J16)*M16 -> 3699.6835 | R16: =Q16+P16-O16 -> 748.88709 | S16: =R17 -> 888.87855 | T16: =IF(B16<=Assumptions!$B$5, ((T15+F16-G16-H16)*(1+K16)-((I16+J16)*D16))/E16, 0) -> 888.88365 | V16: =ABS(T16-S16) -> 0.0051063338 | W16: =IF(B16<=Assumptions!$B$5, IF(V16<0.1,"OK","CHECK"),0) -> OK
B17: =Pricing_Model!C15 -> 7 | C17: =C16+1 -> 41 | D17: =VLOOKUP(C17,Mortality_Table!B13:D113,2,0) -> 0.001808 | E17: =1-D17 -> 0.998192 | F17: =Pricing_Model!W15 -> 1273.1079 | G17: =Pricing_Model!U15 -> 25.462159 | H17: =Pricing_Model!T15 -> 1000 | I17: =Pricing_Model!I15 -> 100000 | J17: =Pricing_Model!J15 -> 500 | K17: =Pricing_Model!K15 -> 0.06 | L17: =Pricing_Model!L15 -> 0.94339623 | M17: =IF(B17<=Assumptions!$B$5,Reserving_Model!L17*Reserving_Model!E17*Reserving_Model!M18+Reserving_Model!L17*Reserving_Model!D17,0) -> 0.037403413 | N17: =IF(B17<=Assumptions!$B$5, 1+N18*L17*E17,0) -> 11.589798 | O17: =N17*(F17-G17) -> 14459.962 | P17: =H17*N17 -> 11589.798 | Q17: =(I17+J17)*M17 -> 3759.043 | R17: =Q17+P17-O17 -> 888.87855 | S17: =R18 -> 1024.8647 | T17: =IF(B17<=Assumptions!$B$5, ((T16+F17-G17-H17)*(1+K17)-((I17+J17)*D17))/E17, 0) -> 1024.8702 | V17: =ABS(T17-S17) -> 0.0054225177 | W17: =IF(B17<=Assumptions!$B$5, IF(V17<0.1,"OK","CHECK"),0) -> OK
B18: =Pricing_Model!C16 -> 8 | C18: =C17+1 -> 42 | D18: =VLOOKUP(C18,Mortality_Table!B14:D114,2,0) -> 0.00189 | E18: =1-D18 -> 0.99811 | F18: =Pricing_Model!W16 -> 1273.1079 | G18: =Pricing_Model!U16 -> 25.462159 | H18: =Pricing_Model!T16 -> 1000 | I18: =Pricing_Model!I16 -> 100000 | J18: =Pricing_Model!J16 -> 500 | K18: =Pricing_Model!K16 -> 0.06 | L18: =Pricing_Model!L16 -> 0.94339623 | M18: =IF(B18<=Assumptions!$B$5,Reserving_Model!L18*Reserving_Model!E18*Reserving_Model!M19+Reserving_Model!L18*Reserving_Model!D18,0) -> 0.037908156 | N18: =IF(B18<=Assumptions!$B$5, 1+N19*L18*E18,0) -> 11.245517 | O18: =N18*(F18-G18) -> 14030.422 | P18: =H18*N18 -> 11245.517 | Q18: =(I18+J18)*M18 -> 3809.7696 | R18: =Q18+P18-O18 -> 1024.8647 | S18: =R19 -> 1161.1106 | T18: =IF(B18<=Assumptions!$B$5, ((T17+F18-G18-H18)*(1+K18)-((I18+J18)*D18))/E18, 0) -> 1161.1164 | V18: =ABS(T18-S18) -> 0.0057587528 | W18: =IF(B18<=Assumptions!$B$5, IF(V18<0.1,"OK","CHECK"),0) -> OK
B19: =Pricing_Model!C17 -> 9 | C19: =C18+1 -> 43 | D19: =VLOOKUP(C19,Mortality_Table!B15:D115,2,0) -> 0.002074 | E19: =1-D19 -> 0.997926 | F19: =Pricing_Model!W17 -> 1273.1079 | G19: =Pricing_Model!U17 -> 25.462159 | H19: =Pricing_Model!T17 -> 1000 | I19: =Pricing_Model!I17 -> 100000 | J19: =Pricing_Model!J17 -> 500 | K19: =Pricing_Model!K17 -> 0.06 | L19: =Pricing_Model!L17 -> 0.94339623 | M19: =IF(B19<=Assumptions!$B$5,Reserving_Model!L19*Reserving_Model!E19*Reserving_Model!M20+Reserving_Model!L19*Reserving_Model!D19,0) -> 0.038365155 | N19: =IF(B19<=Assumptions!$B$5, 1+N20*L19*E19,0) -> 10.880813 | O19: =N19*(F19-G19) -> 13575.401 | P19: =H19*N19 -> 10880.813 | Q19: =(I19+J19)*M19 -> 3855.6981 | R19: =Q19+P19-O19 -> 1161.1106 | S19: =R20 -> 1287.5151 | T19: =IF(B19<=Assumptions!$B$5, ((T18+F19-G19-H19)*(1+K19)-((I19+J19)*D19))/E19, 0) -> 1287.5212 | V19: =ABS(T19-S19) -> 0.0061169646 | W19: =IF(B19<=Assumptions!$B$5, IF(V19<0.1,"OK","CHECK"),0) -> OK
B20: =Pricing_Model!C18 -> 10 | C20: =C19+1 -> 44 | D20: =VLOOKUP(C20,Mortality_Table!B16:D116,2,0) -> 0.002164 | E20: =1-D20 -> 0.997836 | F20: =Pricing_Model!W18 -> 1273.1079 | G20: =Pricing_Model!U18 -> 25.462159 | H20: =Pricing_Model!T18 -> 1000 | I20: =Pricing_Model!I18 -> 100000 | J20: =Pricing_Model!J18 -> 500 | K20: =Pricing_Model!K18 -> 0.06 | L20: =Pricing_Model!L18 -> 0.94339623 | M20: =IF(B20<=Assumptions!$B$5,Reserving_Model!L20*Reserving_Model!E20*Reserving_Model!M21+Reserving_Model!L20*Reserving_Model!D20,0) -> 0.038673273 | N20: =IF(B20<=Assumptions!$B$5, 1+N21*L20*E20,0) -> 10.495429 | O20: =N20*(F20-G20) -> 13094.578 | P20: =H20*N20 -> 10495.429 | Q20: =(I20+J20)*M20 -> 3886.6639 | R20: =Q20+P20-O20 -> 1287.5151 | S20: =R21 -> 1412.8459 | T20: =IF(B20<=Assumptions!$B$5, ((T19+F20-G20-H20)*(1+K20)-((I20+J20)*D20))/E20, 0) -> 1412.8524 | V20: =ABS(T20-S20) -> 0.0064980442 | W20: =IF(B20<=Assumptions!$B$5, IF(V20<0.1,"OK","CHECK"),0) -> OK
B21: =Pricing_Model!C19 -> 11 | C21: =C20+1 -> 45 | D21: =VLOOKUP(C21,Mortality_Table!B17:D117,2,0) -> 0.002433 | E21: =1-D21 -> 0.997567 | F21: =Pricing_Model!W19 -> 1273.1079 | G21: =Pricing_Model!U19 -> 25.462159 | H21: =Pricing_Model!T19 -> 1000 | I21: =Pricing_Model!I19 -> 100000 | J21: =Pricing_Model!J19 -> 500 | K21: =Pricing_Model!K19 -> 0.06 | L21: =Pricing_Model!L19 -> 0.94339623 | M21: =IF(B21<=Assumptions!$B$5,Reserving_Model!L21*Reserving_Model!E21*Reserving_Model!M22+Reserving_Model!L21*Reserving_Model!D21,0) -> 0.038913879 | N21: =IF(B21<=Assumptions!$B$5, 1+N22*L21*E21,0) -> 10.086983 | O21: =N21*(F21-G21) -> 12584.982 | P21: =H21*N21 -> 10086.983 | Q21: =(I21+J21)*M21 -> 3910.8448 | R21: =Q21+P21-O21 -> 1412.8459 | S21: =R22 -> 1519.3012 | T21: =IF(B21<=Assumptions!$B$5, ((T20+F21-G21-H21)*(1+K21)-((I21+J21)*D21))/E21, 0) -> 1519.3081 | V21: =ABS(T21-S21) -> 0.0069047261 | W21: =IF(B21<=Assumptions!$B$5, IF(V21<0.1,"OK","CHECK"),0) -> OK
B22: =Pricing_Model!C20 -> 12 | C22: =C21+1 -> 46 | D22: =VLOOKUP(C22,Mortality_Table!B18:D118,2,0) -> 0.002615 | E22: =1-D22 -> 0.997385 | F22: =Pricing_Model!W20 -> 1273.1079 | G22: =Pricing_Model!U20 -> 25.462159 | H22: =Pricing_Model!T20 -> 1000 | I22: =Pricing_Model!I20 -> 100000 | J22: =Pricing_Model!J20 -> 500 | K22: =Pricing_Model!K20 -> 0.06 | L22: =Pricing_Model!L20 -> 0.94339623 | M22: =IF(B22<=Assumptions!$B$5,Reserving_Model!L22*Reserving_Model!E22*Reserving_Model!M23+Reserving_Model!L22*Reserving_Model!D22,0) -> 0.03891038 | N22: =IF(B22<=Assumptions!$B$5, 1+N23*L22*E22,0) -> 9.6556948 | O22: =N22*(F22-G22) -> 12046.887 | P22: =H22*N22 -> 9655.6948 | Q22: =(I22+J22)*M22 -> 3910.4932 | R22: =Q22+P22-O22 -> 1519.3012 | S22: =R23 -> 1614.3779 | T22: =IF(B22<=Assumptions!$B$5, ((T21+F22-G22-H22)*(1+K22)-((I22+J22)*D22))/E22, 0) -> 1614.3852 | V22: =ABS(T22-S22) -> 0.007338199 | W22: =IF(B22<=Assumptions!$B$5, IF(V22<0.1,"OK","CHECK"),0) -> OK
B23: =Pricing_Model!C21 -> 13 | C23: =C22+1 -> 47 | D23: =VLOOKUP(C23,Mortality_Table!B19:D119,2,0) -> 0.002839 | E23: =1-D23 -> 0.997161 | F23: =Pricing_Model!W21 -> 1273.1079 | G23: =Pricing_Model!U21 -> 25.462159 | H23: =Pricing_Model!T21 -> 1000 | I23: =Pricing_Model!I21 -> 100000 | J23: =Pricing_Model!J21 -> 500 | K23: =Pricing_Model!K21 -> 0.06 | L23: =Pricing_Model!L21 -> 0.94339623 | M23: =IF(B23<=Assumptions!$B$5,Reserving_Model!L23*Reserving_Model!E23*Reserving_Model!M24+Reserving_Model!L23*Reserving_Model!D23,0) -> 0.038731285 | N23: =IF(B23<=Assumptions!$B$5, 1+N24*L23*E23,0) -> 9.1990921 | O23: =N23*(F23-G23) -> 11477.208 | P23: =H23*N23 -> 9199.0921 | Q23: =(I23+J23)*M23 -> 3892.4942 | R23: =Q23+P23-O23 -> 1614.3779 | S23: =R24 -> 1693.2327 | T23: =IF(B23<=Assumptions!$B$5, ((T22+F23-G23-H23)*(1+K23)-((I23+J23)*D23))/E23, 0) -> 1693.2405 | V23: =ABS(T23-S23) -> 0.007800637 | W23: =IF(B23<=Assumptions!$B$5, IF(V23<0.1,"OK","CHECK"),0) -> OK
... B60: =Pricing_Model!C58 -> 50 | C60: =C59+1 -> 84 | D60: =VLOOKUP(C60,Mortality_Table!B56:D156,2,0) -> 0.084093 | E60: =1-D60 -> 0.915907 | F60: =Pricing_Model!W58 -> 0 | G60: =Pricing_Model!U58 -> 0 | H60: =Pricing_Model!T58 -> 0 | I60: =Pricing_Model!I58 -> 0 | J60: =Pricing_Model!J58 -> 0 | K60: =Pricing_Model!K58 -> 0.06 | L60: =Pricing_Model!L58 -> 0.94339623 | M60: =IF(B60<=Assumptions!$B$5,Reserving_Model!L60*Reserving_Model!E60*Reserving_Model!M61+Reserving_Model!L60*Reserving_Model!D60,0) -> 0 | N60: =IF(B60<=Assumptions!$B$5, 1+N61*L60*E60,0) -> 0 | O60: =N60*(F60-G60) -> 0 | P60: =H60*N60 -> 0 | Q60: =(I60+J60)*M60 -> 0 | R60: =Q60+P60-O60 -> 0 | S60: =R61 -> 0 | T60: =IF(B60<=Assumptions!$B$5, ((T59+F60-G60-H60)*(1+K60)-((I60+J60)*D60))/E60, 0) -> 0 | V60: =ABS(T60-S60) -> 0 | W60: =IF(B60<=Assumptions!$B$5, IF(V60<0.1,"OK","CHECK"),0) -> 0

Sheet Interest_Rate_Sensitivity
C3: Interest rate | D3: Premium | E3: % change in Premium | G3: Reserve at time t=10 | H3: % change in Reserve
C4: 0.05 | D4: 1285.2792 | E4: =(D4-$D$5)/$D$5 -> 0.0095602735 | G4: 1464 | H4: =(G4-$G$5)/$G$5 -> 0.036093418
B5: base>> | C5: 0.06 | D5: 1273.1079 | E5: =(D5-$D$5)/$D$5 -> 0 | G5: 1413 | H5: =(G5-$G$5)/$G$5 -> 0
C6: 0.07 | D6: 1261.7291 | E6: =(D6-$D$5)/$D$5 -> -0.0089378621 | G6: 1236 | H6: =(G6-$G$5)/$G$5 -> -0.12526539

Sheet Model_Summary
B3: Input Section | K3: Output Section
A5: Scenario | B5: Entry Age | C5: Term | D5: Sum Assured | E5: Interest rate | F5: Expenses | G5: Commission | K5: Premium | L5: EPV Benefits | M5: EPV Premiums | N5: Reserve at t= 10 | O5: Max Reconciliation Error | Q5: Model Validation
A6: 1 | B6: =Assumptions!B3 -> 35 | C6: =Assumptions!B5 -> 25 | D6: =Assumptions!B6 -> 100000 | E6: =Assumptions!B7 -> 0.06 | F6: =Assumptions!B8 -> 1000 | G6: =Assumptions!B10 -> 0.02 | K6: =Pricing_Model!$T$2 -> 1273.1079 | L6: =Pricing_Model!$M$60 -> 3293.88 | M6: =Pricing_Model!$Y$60 -> 16594.67 | N6: =Reserving_Model!S20 -> 1412.8459 | O6: =Reserving_Model!Y5 -> 0.016656322 | Q6: =IF(O6<0.1,"VALIDATED", "CHECK MODEL") -> VALIDATED
